setup.py
distributions/Binomialdistribution.py
distributions/Gaussiandistribution.py
distributions/Generaldistribution.py
distributions/__init__.py
vics_distributions.egg-info/PKG-INFO
vics_distributions.egg-info/SOURCES.txt
vics_distributions.egg-info/dependency_links.txt
vics_distributions.egg-info/not-zip-safe
vics_distributions.egg-info/top_level.txt